eclipse_zenoh_nightly-0.7.0rc20230328.dist-info/METADATA
eclipse_zenoh_nightly-0.7.0rc20230328.dist-info/WHEEL
eclipse_zenoh_nightly-0.7.0rc20230328.dist-info/license_files/LICENSE
eclipse_zenoh_nightly-0.7.0rc20230328.dist-info/license_files/NOTICE.md
zenoh/queryable.py
zenoh/closures.py
zenoh/value.py
zenoh/enums.py
zenoh/config.py
zenoh/__init__.py
zenoh/keyexpr.py
zenoh/session.py
zenoh/zenoh.abi3.so
eclipse_zenoh_nightly-0.7.0rc20230328.dist-info/RECORD
