Metadata-Version: 2.1
Name: eclipse-zenoh-nightly
Version: 0.7.0rc20230328
Classifier: Programming Language :: Python :: 3 :: Only
Classifier: Programming Language :: Python :: 3.7
Classifier: Programming Language :: Python :: 3.8
Classifier: Programming Language :: Python :: 3.9
Classifier: Programming Language :: Python :: 3.10
Classifier: Programming Language :: Rust
Classifier: Intended Audience :: Developers
Classifier: Development Status :: 4 - Beta
Classifier: Topic :: System :: Networking
Classifier: License :: OSI Approved :: Apache Software License
Classifier: License :: OSI Approved :: Eclipse Public License 2.0 (EPL-2.0)
Classifier: Operating System :: POSIX :: Linux
Classifier: Operating System :: MacOS :: MacOS X
Classifier: Operating System :: Microsoft :: Windows
License-File: LICENSE
License-File: NOTICE.md
Summary: The python API for Eclipse zenoh
Author: kydos <angelo@icorsaro.net>, Julien Enoch <julien@enoch.fr>, Olivier Hécart <olivier.hecart@adlinktech.com>, Luca Cominardi <luca.cominardi@gmail.com>, Pierre Avital <pierre.avital@adlinktech.com>
Author-email: kydos <angelo@icorsaro.net>, Julien Enoch <julien@enoch.fr>, Olivier Hécart <olivier.hecart@adlinktech.com>, Luca Cominardi <luca.cominardi@gmail.com>, Pierre Avital <pierre.avital@adlinktech.com>
Requires-Python: >=3.7
Project-URL: Documentation, https://readthedocs.org/projects/zenoh-python/
Project-URL: Bug Tracker, https://github.com/eclipse-zenoh/zenoh-python/issues
Project-URL: Source Code, https://github.com/eclipse-zenoh/zenoh-python
